telcolib/__init__.py
telcolib/validator.py
tests/__init__.py
tests/test_validator.py
telcolib-0.2.dist-info/LICENSE
telcolib-0.2.dist-info/METADATA
telcolib-0.2.dist-info/WHEEL
telcolib-0.2.dist-info/top_level.txt
telcolib-0.2.dist-info/RECORD
