Metadata-Version: 2.1
Name: telcolib
Version: 0.2
Summary: A phone number validation library for multiple countries
Home-page: https://github.com/yourusername/telcolib
Author: Don Johnson
Author-email: dj@codetestcode.io
License: MIT
Keywords: phone number validation telecommunications
Classifier: Development Status :: 3 - Alpha
Classifier: Intended Audience :: Developers
Classifier: Topic :: Software Development :: Libraries
Classifier: License :: OSI Approved :: MIT License
Classifier: Programming Language :: Python :: 3
Requires-Python: >=3.6
License-File: LICENSE
